{
  "last_run": "2026-07-21T13:39:51.530980",
  "feeds_checked": {
    "https://techcrunch.com/category/artificial-intelligence/feed/": "2026-07-21T13:39:48.534145",
    "https://tomtunguz.com/index.xml": "2026-07-21T13:39:48.568932",
    "https://simonwillison.net/atom/everything/": "2026-07-21T13:39:50.135853",
    "https://future.com/feed/": "2026-07-21T13:39:48.478950",
    "https://garymarcus.substack.com/feed": "2026-07-07T00:58:59.779004",
    "https://lastweekin.ai/feed": "2026-07-21T13:39:50.060235",
    "https://importai.substack.com/feed": "2026-07-07T00:58:59.709317",
    "https://www.interconnects.ai/feed": "2026-07-21T13:39:50.430423",
    "https://www.technologyreview.com/topic/artificial-intelligence/feed/": "2026-07-21T13:39:49.956137",
    "https://www.latent.space/feed": "2026-07-21T13:39:49.198027",
    "https://www.theverge.com/rss/ai-artificial-intelligence/index.xml": "2026-07-21T13:39:49.924205",
    "https://venturebeat.com/category/ai/feed/": "2026-07-21T13:39:50.472435",
    "https://huggingface.co/blog/feed.xml": "2026-07-21T13:39:50.309883",
    "https://magazine.sebastianraschka.com/feed": "2026-07-21T13:39:49.889302",
    "https://www.oneusefulthing.org/feed": "2026-07-21T13:39:50.670446",
    "https://blog.eladgil.com/feed": "2026-07-21T13:39:48.960919",
    "https://www.sequoiacap.com/feed/": "2026-07-21T13:39:50.787237",
    "https://www.aisnakeoil.com/feed": "2026-07-21T13:39:51.166050",
    "https://arstechnica.com/ai/feed/": "2026-07-21T13:39:50.817624",
    "https://the-decoder.com/feed/": "2026-07-21T13:39:51.518412",
    "https://menlovc.com/feed/": "2026-07-21T13:39:48.620236",
    "https://www.saastr.com/feed/": "2026-07-21T13:39:49.997186",
    "https://www.insightpartners.com/feed/": "2026-07-07T00:58:59.377094",
    "https://press.airstreet.com/feed": "2026-07-21T13:39:49.319145",
    "https://foundersfund.com/feed/": "2026-07-21T13:39:50.720796",
    "https://sarahtavel.substack.com/feed": "2026-07-07T00:59:00.136379",
    "https://www.radical.vc/feed/": "2026-07-21T13:39:50.445487"
  },
  "signals_generated": 979
}