{
  "last_run": "2026-07-13T13:20:51.515668",
  "feeds_checked": {
    "https://www.reddit.com/r/cybersecurity/.rss": "2026-07-13T13:20:20.741548",
    "https://www.reddit.com/r/netsec/.rss": "2026-07-13T13:20:21.394792",
    "https://techcrunch.com/author/zack-whittaker/feed/": "2026-07-13T13:20:21.766557",
    "https://techcrunch.com/category/startups/feed/": "2026-07-13T13:20:21.859036",
    "https://techcrunch.com/category/security/feed/": "2026-07-13T13:20:21.779789",
    "https://techcrunch.com/author/lorenzo-franceschi-bicchierai/feed/": "2026-07-13T13:20:21.844097",
    "https://www.schneier.com/feed/": "2026-07-13T13:20:23.165565",
    "https://feeds.twit.tv/sn.xml": "2026-07-13T13:20:24.556409",
    "https://www.wired.com/feed/category/security/latest/rss": "2026-07-13T13:20:21.874737",
    "https://sequoiacap.com/feed/": "2026-07-13T13:20:21.593438",
    "https://news.ycombinator.com/rss": "2026-07-13T13:20:23.415686",
    "https://www.helpnetsecurity.com/feed/": "2026-07-13T13:20:24.477714",
    "https://www.youtube.com/feeds/videos.xml?channel_id=UCVeW9qkBjo3zosnqUbG7CFw": "2026-07-13T13:20:22.610178",
    "https://sed-cms.broadcom.com/rss/v1/blogs/rss.xml": "2026-07-07T00:58:26.244161",
    "https://www.cisecurity.org/feed/advisories": "2026-07-13T13:20:25.342235",
    "https://www.schneier.com/blog/atom.xml": "2026-07-13T13:20:23.452359",
    "https://www.malwaretech.com/feed": "2026-07-13T13:20:22.750045",
    "https://www.nist.gov/blogs/cybersecurity-insights/rss.xml": "2026-07-13T13:20:24.706646",
    "https://ventureinsecurity.net/feed": "2026-07-13T13:20:26.698692",
    "https://risky.biz/feeds/risky-business/": "2026-07-13T13:20:23.141722",
    "https://www.troyhunt.com/rss/": "2026-07-13T13:20:25.397962",
    "https://ballisticventures.com/feed/": "2026-07-13T13:20:21.638705",
    "https://www.eff.org/rss/updates.xml": "2026-07-13T13:20:22.543045",
    "https://www.zetter-zeroday.com/feed/": "2026-07-13T13:20:23.247021",
    "https://news.crunchbase.com/feed/": "2026-07-13T13:20:22.833512",
    "https://www.producthunt.com/feed": "2026-07-13T13:20:22.658379",
    "http://feeds.feedburner.com/govtech/blogs/lohrmann_on_infrastructure": "2026-07-13T13:20:24.647825",
    "https://grahamcluley.com/feed/": "2026-07-13T13:20:22.781529",
    "https://krebsonsecurity.com/feed/": "2026-07-13T13:20:22.743099",
    "https://medium.com/feed/tag/cybersecurity": "2026-07-13T13:20:21.683989",
    "https://redcanary.com/blog/feed/": "2026-07-13T13:20:23.173831",
    "https://perspectives.acrewcapital.com/feed": "2026-07-13T13:20:22.205312",
    "https://feeds.feedburner.com/TheHackersNews": "2026-07-13T13:20:22.596611",
    "https://feeds.feedburner.com/TroyHunt": "2026-07-13T13:20:22.577191",
    "https://nao-sec.org/feed": "2026-07-13T13:20:25.215746",
    "https://isc.sans.edu/rssfeed_full.xml": "2026-07-13T13:20:24.671876",
    "https://www.youtube.com/feeds/videos.xml?channel_id=UC0ArlFuFYMpEewyRBzdLHiw": "2026-07-13T13:20:22.625535",
    "https://raincapital.substack.com/feed": "2026-07-07T00:58:26.857320",
    "https://www.theguardian.com/technology/data-computer-security/rss": "2026-07-13T13:20:25.370779",
    "https://www.bitdefender.com/blog/api/rss/labs/": "2026-07-13T13:20:26.211701",
    "https://www.bellingcat.com/feed/": "2026-07-13T13:20:24.967937",
    "https://medium.com/feed/@sebdraven": "2026-07-13T13:20:21.665024",
    "https://medium.com/feed/lightspeed-venture-partners": "2026-07-13T13:20:22.103912",
    "https://www.globenewswire.com/RssFeed/subjectcode/35-Technology/feedTitle/GlobeNewswire%20-%20Technology": "2026-07-13T13:20:23.403892",
    "https://medium.com/feed/anton-on-security": "2026-07-13T13:20:22.276340",
    "https://www.grahamcluley.com/feed/": "2026-07-13T13:20:26.008224",
    "https://therecord.media/feed/": "2026-07-13T13:20:23.424547",
    "https://medium.com/feed/tag/infosec": "2026-07-13T13:20:22.295753",
    "https://danielmiessler.com/feed/": "2026-07-13T13:20:24.417328",
    "https://arstechnica.com/tag/security/feed/": "2026-07-13T13:20:24.603002",
    "https://arstechnica.com/author/dan-goodin/feed/": "2026-07-13T13:20:24.642882",
    "http://www.malware-traffic-analysis.net/blog-entries.rss": "2026-07-13T13:20:27.571043",
    "https://www.prnewswire.com/rss/information-technology-latest-news/information-technology-latest-news-list.rss": "2026-07-13T13:20:23.192451",
    "https://www.zdnet.com/topic/security/rss.xml": "2026-07-13T13:20:26.882031",
    "https://www.proofpoint.com/us/rss.xml": "2026-07-13T13:20:25.992588",
    "https://www.upguard.com/news/rss.xml": "2026-07-13T13:20:27.621096",
    "https://feeds.megaphone.fm/darknetdiaries": "2026-07-13T13:20:25.983695",
    "https://sensepost.com/rss.xml": "2026-07-13T13:20:26.557086",
    "https://research.checkpoint.com/feed/": "2026-07-13T13:20:25.562364",
    "https://blog.cloudflare.com/tag/security/rss": "2026-07-13T13:20:27.788773",
    "https://blog.eclecticiq.com/rss.xml": "2026-07-13T13:20:27.587184",
    "https://blog.0patch.com/feeds/posts/default": "2026-07-13T13:20:28.923513",
    "https://feeds.feedburner.com/securityweek": "2026-07-13T13:20:27.177424",
    "https://www.sentinelone.com/labs/feed/": "2026-07-13T13:20:26.201309",
    "http://www.techrepublic.com/rssfeeds/topic/security/?feedType=rssfeeds": "2026-07-13T13:20:29.069963",
    "https://blog.fox-it.com/feed/": "2026-07-13T13:20:27.450989",
    "https://blog.qualys.com/feed": "2026-07-13T13:20:24.798486",
    "https://blog.virustotal.com/feeds/posts/default": "2026-07-13T13:20:26.874326",
    "http://feeds.trendmicro.com/TrendMicroSimplySecurity": "2026-07-13T13:20:24.998869",
    "https://us-cert.cisa.gov/ics/advisories/advisories.xml": "2026-07-07T00:58:27.138544",
    "https://threatpost.com/feed/": "2026-07-13T13:20:26.105746",
    "https://medium.com/feed/@edsim": "2026-07-13T13:20:23.492069",
    "http://feeds.feedburner.com/feedburner/Talos": "2026-07-13T13:20:25.318900",
    "https://www.upguard.com/breaches/rss.xml": "2026-07-13T13:20:27.994013",
    "http://www.infosecurity-magazine.com/rss/news/": "2026-07-13T13:20:29.384099",
    "https://cofense.com/feed/": "2026-07-13T13:20:26.095730",
    "https://www.hackread.com/feed/": "2026-07-13T13:20:29.180823",
    "https://www.microsoft.com/security/blog/feed/": "2026-07-13T13:20:27.547083",
    "https://www.virusbulletin.com/rss": "2026-07-13T13:20:27.459564",
    "http://www.darknet.org.uk/feed/": "2026-07-13T13:20:28.883979",
    "https://blogs.cisco.com/security/feed": "2026-07-13T13:20:27.557675",
    "https://blog.malwarebytes.com/feed/": "2026-07-13T13:20:29.163615",
    "https://us-cert.cisa.gov/ncas/alerts.xml": "2026-07-07T00:58:28.263222",
    "https://danielmiessler.com/feed": "2026-07-13T13:20:28.877124",
    "https://www.smashingsecurity.com/rss": "2026-07-13T13:20:34.368098",
    "http://securityaffairs.co/wordpress/feed": "2026-07-13T13:20:35.887220",
    "https://googleonlinesecurity.blogspot.com/atom.xml": "2026-07-13T13:20:34.565967",
    "https://securelist.com/feed/": "2026-07-13T13:20:27.962838",
    "https://www.paloaltonetworks.com/blog/rss": "2026-07-13T13:20:28.995890",
    "https://us-cert.cisa.gov/ncas/analysis-reports.xml": "2026-07-07T00:58:30.460486",
    "https://blog.quarkslab.com/feeds/all.rss.xml": "2026-07-13T13:20:36.802696",
    "https://us-cert.cisa.gov/ncas/current-activity.xml": "2026-07-07T00:58:30.650592",
    "https://googleprojectzero.blogspot.com/feeds/posts/default": "2026-07-13T13:20:35.836764",
    "https://socprime.com/blog/feed/": "2026-07-13T13:20:29.037799",
    "https://risky.biz/feeds/risky-business-news/": "2026-07-13T13:20:36.922547",
    "https://tldrsec.com/feed.xml": "2026-07-13T13:20:37.977111",
    "http://eset.com/int/rss.xml": "2026-07-13T13:20:34.580893"
  },
  "signals_generated": 3518
}