{
  "last_run": "2026-07-24T15:23:13.740965",
  "feeds_checked": {
    "https://esgnews.com/feed/": "2026-07-24T15:23:11.813670",
    "https://www.esgtoday.com/feed/": "2026-07-24T15:23:11.955928",
    "https://ssir.org/site/rss_2.0": "2026-07-24T15:23:12.226888",
    "https://www.pioneerspost.com/feed": "2026-07-24T15:23:12.073197",
    "https://impact-investor.com/feed/": "2026-07-24T15:23:12.107239",
    "https://impactalpha.com/feed/": "2026-07-07T19:50:22.011746",
    "https://www.takwinventures.com/feed/": "2026-07-24T15:23:12.741875",
    "https://www.bridgesfundmanagement.com/feed/": "2026-07-24T15:23:12.676149",
    "https://nextbillion.net/feed/": "2026-07-24T15:23:12.911075",
    "https://www.socialenterprise.org.uk/feed/": "2026-07-24T15:23:13.735047"
  },
  "signals_generated": 220
}