{
  "last_run": "2026-07-19T11:54:42.217230",
  "feeds_checked": {
    "https://techcrunch.com/category/fintech/feed/": "2026-07-19T11:54:40.798348",
    "https://www.paymentsdive.com/feeds/news/": "2026-07-19T11:54:41.757414",
    "https://future.com/feed/": "2026-07-19T11:54:40.903252",
    "https://www.qedinvestors.com/blog/rss.xml": "2026-07-19T11:54:41.750988",
    "https://www.bankingdive.com/feeds/news/": "2026-07-19T11:54:41.762580",
    "https://www.netinterest.co/feed": "2026-07-19T11:54:41.811097",
    "https://fintechbusinessweekly.substack.com/feed": "2026-07-07T00:58:56.759246",
    "https://lex.substack.com/feed": "2026-07-07T00:58:57.074230",
    "https://newsletter.fintechtakes.com/feed": "2026-07-19T11:54:41.203659",
    "https://bettertomorrow.substack.com/feed": "2026-07-07T00:58:57.237440",
    "https://www.finextra.com/rss/headlines.aspx": "2026-07-19T11:54:41.986347",
    "https://www.crowdfundinsider.com/feed/": "2026-07-19T11:54:41.939177",
    "https://sifted.eu/feed": "2026-07-19T11:54:42.203888",
    "https://tearsheet.co/feed": "2026-07-19T11:54:41.614216",
    "https://www.pymnts.com/feed/": "2026-07-19T11:54:42.019023",
    "https://thepaymentsassociation.org/feed/": "2026-07-07T00:58:59.000248",
    "https://www.generalist.com/feed": "2026-07-19T11:54:41.928973",
    "https://kwokchain.com/feed/": "2026-07-19T11:54:40.992596",
    "https://www.notboring.co/feed": "2026-07-19T11:54:41.522911",
    "https://ronshevlin.substack.com/feed": "2026-07-07T00:58:57.234482",
    "https://tearsheet.co/feed/": "2026-07-19T11:54:41.568351",
    "https://sarahtavel.substack.com/feed": "2026-07-07T00:58:57.362824",
    "https://cbinsights.com/research/feed/": "2026-07-19T11:54:41.708883"
  },
  "signals_generated": 1084
}