{
  "last_run": "2026-07-19T20:42:00.651454",
  "feeds_checked": {
    "https://techcrunch.com/category/fintech/feed/": "2026-07-19T20:41:59.491893",
    "https://www.paymentsdive.com/feeds/news/": "2026-07-19T20:41:59.497745",
    "https://future.com/feed/": "2026-07-19T20:41:59.624081",
    "https://www.qedinvestors.com/blog/rss.xml": "2026-07-19T20:41:59.530428",
    "https://www.bankingdive.com/feeds/news/": "2026-07-19T20:42:00.141087",
    "https://www.netinterest.co/feed": "2026-07-19T20:42:00.134701",
    "https://fintechbusinessweekly.substack.com/feed": "2026-07-07T00:58:56.759246",
    "https://lex.substack.com/feed": "2026-07-07T00:58:57.074230",
    "https://newsletter.fintechtakes.com/feed": "2026-07-19T20:41:59.477687",
    "https://bettertomorrow.substack.com/feed": "2026-07-07T00:58:57.237440",
    "https://www.finextra.com/rss/headlines.aspx": "2026-07-19T20:42:00.264563",
    "https://www.crowdfundinsider.com/feed/": "2026-07-19T20:42:00.248494",
    "https://sifted.eu/feed": "2026-07-19T20:41:59.687099",
    "https://tearsheet.co/feed": "2026-07-19T20:42:00.057665",
    "https://www.pymnts.com/feed/": "2026-07-19T20:42:00.637773",
    "https://thepaymentsassociation.org/feed/": "2026-07-07T00:58:59.000248",
    "https://www.generalist.com/feed": "2026-07-19T20:41:59.272453",
    "https://kwokchain.com/feed/": "2026-07-19T20:41:59.149780",
    "https://www.notboring.co/feed": "2026-07-19T20:42:00.007501",
    "https://ronshevlin.substack.com/feed": "2026-07-07T00:58:57.234482",
    "https://tearsheet.co/feed/": "2026-07-19T20:41:59.672866",
    "https://sarahtavel.substack.com/feed": "2026-07-07T00:58:57.362824",
    "https://cbinsights.com/research/feed/": "2026-07-19T20:42:00.238825"
  },
  "signals_generated": 1090
}