{
  "last_run": "2026-07-09T21:20:37.123672",
  "feeds_checked": {
    "https://techcrunch.com/category/climate/feed/": "2026-07-09T21:20:35.506344",
    "https://electrek.co/feed/": "2026-07-09T21:20:35.485706",
    "https://newsletter.mcj.vc/feed": "2026-07-09T21:20:35.678771",
    "https://cleantechnica.com/feed/": "2026-07-09T21:20:35.872436",
    "https://www.carbonbrief.org/feed/": "2026-07-09T21:20:35.998596",
    "https://www.canarymedia.com/feed": "2026-07-09T21:20:35.829282",
    "https://insideclimatenews.org/feed/": "2026-07-07T00:59:03.077666",
    "https://www.theclimatebrink.com/feed": "2026-07-09T21:20:36.177003",
    "https://heated.world/feed": "2026-07-09T21:20:35.258489",
    "https://grist.org/feed/": "2026-07-09T21:20:36.777765",
    "https://www.volts.wtf/feed": "2026-07-09T21:20:36.429449",
    "https://www.latitudemedia.com/feed": "2026-07-09T21:20:35.785510",
    "https://www.ctvc.co/feed": "2026-07-09T21:20:36.623049",
    "https://www.sustainabilitybynumbers.com/feed": "2026-07-07T00:59:03.356001",
    "https://www.lowercarbon.com/feed": "2026-07-09T21:20:36.825577",
    "https://www.watttime.org/feed": "2026-07-09T21:20:37.115381",
    "https://www.utilitydive.com/feeds/news/": "2026-07-09T21:20:35.684823",
    "https://www.canarymedia.com/rss.xml": "2026-07-09T21:20:36.464087",
    "https://www.distilled.earth/feed": "2026-07-09T21:20:35.363750",
    "https://climatedrift.substack.com/feed": "2026-07-07T00:59:02.872989",
    "https://climatepapa.substack.com/feed": "2026-07-07T00:59:03.500391"
  },
  "signals_generated": 549
}