{
  "last_run": "2026-07-22T19:10:34.390310",
  "feeds_checked": {
    "https://techcrunch.com/category/space/feed/": "2026-07-22T19:10:33.285545",
    "https://spacenews.com/feed/": "2026-07-22T19:10:33.637336",
    "https://spacecapital.substack.com/feed": "2026-07-07T00:59:06.817844",
    "https://feeds.arstechnica.com/arstechnica/science": "2026-07-22T19:10:33.362316",
    "https://www.universetoday.com/feed/": "2026-07-22T19:10:33.674050",
    "https://payloadspace.com/feed/": "2026-07-22T19:10:33.664750",
    "https://spaceambition.substack.com/feed": "2026-07-07T00:59:06.623412",
    "https://www.space.com/feeds/all": "2026-07-22T19:10:33.879962",
    "https://spacepolicyonline.com/feed/": "2026-07-22T19:10:34.101910",
    "https://www.nasaspaceflight.com/feed/": "2026-07-22T19:10:34.193591",
    "https://seraphim.vc/feed/": "2026-07-22T19:10:33.941002",
    "https://orbitalindex.com/feed.xml": "2026-07-22T19:10:33.586956",
    "https://spacedotbiz.substack.com/feed": "2026-07-07T00:59:06.702661",
    "https://payload.substack.com/feed": "2026-07-07T00:59:06.783083",
    "https://www.satellitetoday.com/feed/": "2026-07-07T00:59:06.519971",
    "https://foundersfund.com/feed/": "2026-07-22T19:10:34.138552",
    "https://europeanspaceflight.com/feed/": "2026-07-22T19:10:34.382075"
  },
  "signals_generated": 775
}